pyroblox/__init__.py
pyroblox/account.py
pyroblox/login.py
pyroblox/models.py
pyroblox/tools.py
pyroblox/game/game.py
pyroblox/game/gamepass.py
pyroblox/game/server.py
pyroblox/group/auditlog.py
pyroblox/group/group.py
pyroblox/group/groupshout.py
pyroblox/group/joinrequest.py
pyroblox/group/member.py
pyroblox/group/role.py
pyroblox/group/wallpost.py
pyroblox/item/item.py
pyroblox/item/limited.py
pyroblox/message/message.py
pyroblox/trade/trade.py
pyroblox/trade/tradeinformation.py
pyroblox/user/friendrequest.py
pyroblox/user/user.py
pyroblox/utils/errors.py
pyroblox/utils/functions.py
pyroblox/utils/data/AssetTypes.py
pyroblox_viown-0.4.5.dist-info/LICENSE
pyroblox_viown-0.4.5.dist-info/METADATA
pyroblox_viown-0.4.5.dist-info/WHEEL
pyroblox_viown-0.4.5.dist-info/top_level.txt
pyroblox_viown-0.4.5.dist-info/RECORD
