Metadata-Version: 2.1
Name: pyroblox-viown
Version: 0.4.5
Summary: An API Wrapper for roblox.com
Home-page: https://github.com/viown/pyroblox
Author: viown
Author-email: sperd620@gmail.com
License: UNKNOWN
Platform: UNKNOWN
Requires-Python: >=3.7
